[
  {
    "time": 1773316165.584253,
    "rss_mb": 1.31072,
    "vms_mb": 6.397952,
    "nprocs": 1
  },
  {
    "time": 1773316166.6669176,
    "rss_mb": 203.30496,
    "vms_mb": 413.032448,
    "nprocs": 2
  },
  {
    "time": 1773316167.677053,
    "rss_mb": 203.30496,
    "vms_mb": 413.032448,
    "nprocs": 2
  },
  {
    "time": 1773316168.760732,
    "rss_mb": 203.30496,
    "vms_mb": 413.032448,
    "nprocs": 2
  },
  {
    "time": 1773316169.8173263,
    "rss_mb": 203.30496,
    "vms_mb": 413.032448,
    "nprocs": 2
  },
  {
    "time": 1773316170.8630834,
    "rss_mb": 203.30496,
    "vms_mb": 413.032448,
    "nprocs": 2
  },
  {
    "time": 1773316171.946694,
    "rss_mb": 203.30496,
    "vms_mb": 413.032448,
    "nprocs": 2
  },
  {
    "time": 1773316172.9497218,
    "rss_mb": 203.30496,
    "vms_mb": 413.032448,
    "nprocs": 2
  },
  {
    "time": 1773316174.0333605,
    "rss_mb": 203.30496,
    "vms_mb": 413.032448,
    "nprocs": 2
  },
  {
    "time": 1773316175.0530965,
    "rss_mb": 203.30496,
    "vms_mb": 413.032448,
    "nprocs": 2
  },
  {
    "time": 1773316176.1369264,
    "rss_mb": 203.30496,
    "vms_mb": 413.032448,
    "nprocs": 2
  },
  {
    "time": 1773316177.1578867,
    "rss_mb": 203.30496,
    "vms_mb": 413.032448,
    "nprocs": 2
  },
  {
    "time": 1773316178.1881251,
    "rss_mb": 203.30496,
    "vms_mb": 413.032448,
    "nprocs": 2
  },
  {
    "time": 1773316179.2708302,
    "rss_mb": 203.30496,
    "vms_mb": 413.032448,
    "nprocs": 2
  },
  {
    "time": 1773316180.3015504,
    "rss_mb": 203.30496,
    "vms_mb": 413.032448,
    "nprocs": 2
  },
  {
    "time": 1773316181.3127093,
    "rss_mb": 203.30496,
    "vms_mb": 413.032448,
    "nprocs": 2
  },
  {
    "time": 1773316182.3964493,
    "rss_mb": 203.30496,
    "vms_mb": 413.032448,
    "nprocs": 2
  },
  {
    "time": 1773316183.4801407,
    "rss_mb": 203.30496,
    "vms_mb": 413.032448,
    "nprocs": 2
  },
  {
    "time": 1773316184.4923995,
    "rss_mb": 203.30496,
    "vms_mb": 413.032448,
    "nprocs": 2
  },
  {
    "time": 1773316185.5441604,
    "rss_mb": 203.30496,
    "vms_mb": 413.032448,
    "nprocs": 2
  },
  {
    "time": 1773316184.2668436,
    "rss_mb": 203.30496,
    "vms_mb": 413.032448,
    "nprocs": 2
  },
  {
    "time": 1773316185.2681763,
    "rss_mb": 203.30496,
    "vms_mb": 413.032448,
    "nprocs": 2
  },
  {
    "time": 1773316186.2696264,
    "rss_mb": 203.30496,
    "vms_mb": 413.032448,
    "nprocs": 2
  },
  {
    "time": 1773316187.3290832,
    "rss_mb": 203.30496,
    "vms_mb": 413.032448,
    "nprocs": 2
  },
  {
    "time": 1773316188.3588586,
    "rss_mb": 203.30496,
    "vms_mb": 413.032448,
    "nprocs": 2
  },
  {
    "time": 1773316189.4427245,
    "rss_mb": 203.30496,
    "vms_mb": 413.032448,
    "nprocs": 2
  },
  {
    "time": 1773316190.4924386,
    "rss_mb": 203.30496,
    "vms_mb": 413.032448,
    "nprocs": 2
  },
  {
    "time": 1773316191.5175636,
    "rss_mb": 203.30496,
    "vms_mb": 413.032448,
    "nprocs": 2
  },
  {
    "time": 1773316192.6012182,
    "rss_mb": 203.30496,
    "vms_mb": 413.032448,
    "nprocs": 2
  },
  {
    "time": 1773316193.685363,
    "rss_mb": 203.30496,
    "vms_mb": 413.032448,
    "nprocs": 2
  },
  {
    "time": 1773316194.6865962,
    "rss_mb": 203.30496,
    "vms_mb": 413.032448,
    "nprocs": 2
  },
  {
    "time": 1773316195.736031,
    "rss_mb": 203.30496,
    "vms_mb": 413.032448,
    "nprocs": 2
  },
  {
    "time": 1773316196.7755125,
    "rss_mb": 203.30496,
    "vms_mb": 413.032448,
    "nprocs": 2
  },
  {
    "time": 1773316197.8585417,
    "rss_mb": 203.30496,
    "vms_mb": 413.032448,
    "nprocs": 2
  },
  {
    "time": 1773316198.879338,
    "rss_mb": 203.30496,
    "vms_mb": 413.032448,
    "nprocs": 2
  },
  {
    "time": 1773316199.9448707,
    "rss_mb": 203.30496,
    "vms_mb": 413.032448,
    "nprocs": 2
  },
  {
    "time": 1773316201.0284984,
    "rss_mb": 203.30496,
    "vms_mb": 413.032448,
    "nprocs": 2
  },
  {
    "time": 1773316202.1122673,
    "rss_mb": 203.30496,
    "vms_mb": 413.032448,
    "nprocs": 2
  },
  {
    "time": 1773316203.1135774,
    "rss_mb": 203.30496,
    "vms_mb": 413.032448,
    "nprocs": 2
  },
  {
    "time": 1773316204.150923,
    "rss_mb": 203.30496,
    "vms_mb": 413.032448,
    "nprocs": 2
  },
  {
    "time": 1773316205.226141,
    "rss_mb": 203.30496,
    "vms_mb": 413.032448,
    "nprocs": 2
  },
  {
    "time": 1773316206.3096678,
    "rss_mb": 203.30496,
    "vms_mb": 413.032448,
    "nprocs": 2
  },
  {
    "time": 1773316207.3715448,
    "rss_mb": 203.30496,
    "vms_mb": 413.032448,
    "nprocs": 2
  },
  {
    "time": 1773316208.423861,
    "rss_mb": 203.30496,
    "vms_mb": 413.032448,
    "nprocs": 2
  },
  {
    "time": 1773316209.5069234,
    "rss_mb": 203.30496,
    "vms_mb": 413.032448,
    "nprocs": 2
  },
  {
    "time": 1773316210.5908506,
    "rss_mb": 203.30496,
    "vms_mb": 413.032448,
    "nprocs": 2
  },
  {
    "time": 1773316211.5923367,
    "rss_mb": 203.30496,
    "vms_mb": 413.032448,
    "nprocs": 2
  },
  {
    "time": 1773316212.6222978,
    "rss_mb": 203.30496,
    "vms_mb": 413.032448,
    "nprocs": 2
  },
  {
    "time": 1773316213.7058976,
    "rss_mb": 203.30496,
    "vms_mb": 413.032448,
    "nprocs": 2
  },
  {
    "time": 1773316214.7127414,
    "rss_mb": 203.30496,
    "vms_mb": 413.032448,
    "nprocs": 2
  },
  {
    "time": 1773316215.7962475,
    "rss_mb": 203.30496,
    "vms_mb": 413.032448,
    "nprocs": 2
  },
  {
    "time": 1773316214.6304708,
    "rss_mb": 203.30496,
    "vms_mb": 413.032448,
    "nprocs": 2
  },
  {
    "time": 1773316215.6436958,
    "rss_mb": 203.30496,
    "vms_mb": 413.032448,
    "nprocs": 2
  },
  {
    "time": 1773316216.6454995,
    "rss_mb": 203.30496,
    "vms_mb": 413.032448,
    "nprocs": 2
  },
  {
    "time": 1773316217.6477296,
    "rss_mb": 203.30496,
    "vms_mb": 413.032448,
    "nprocs": 2
  },
  {
    "time": 1773316218.7312758,
    "rss_mb": 203.30496,
    "vms_mb": 413.032448,
    "nprocs": 2
  },
  {
    "time": 1773316219.8152497,
    "rss_mb": 203.30496,
    "vms_mb": 413.032448,
    "nprocs": 2
  },
  {
    "time": 1773316220.8172216,
    "rss_mb": 203.30496,
    "vms_mb": 413.032448,
    "nprocs": 2
  }
]